srlz/__init__.py
srlz/py.typed
srlz/serialization.py
srlz/utils.py
srlz-0.1.1.dist-info/METADATA
srlz-0.1.1.dist-info/WHEEL
srlz-0.1.1.dist-info/RECORD
