Metadata-Version: 2.3
Name: srlz
Version: 0.1.1
Summary: A Customizable Serialization Framework
Author: Dan Gittik
Author-email: dan.gittik@gmail.com
Requires-Python: >=3.12
Classifier: Programming Language :: Python :: 3
Classifier: Programming Language :: Python :: 3.12
Classifier: Programming Language :: Python :: 3.13
